rippleCounter.v
module up_down_counter (
    input clk,
    input reset,
    input up_down,  // 1 for up, 0 for down
    output [2:0] count
);
    reg [2:0] count_reg;

    always @(posedge clk or posedge reset) begin
        if (reset) begin
            count_reg <= 3'b000;
        end else if (up_down) begin
            count_reg <= count_reg + 1;
        end else begin
            count_reg <= count_reg - 1;
        end
    end

    assign count = count_reg;

endmodule

up_down_rippleCounter_tb.v
module testbench;
    reg clk, reset, up_down;
    wire [2:0] count;
    up_down_counter udc ( .clk(clk), .reset(reset), .up_down(up_down), .count(count));
    // Clock generation
    initial begin
        clk = 0;
        forever #5 clk = ~clk;
    end
    // Stimulus
    initial begin
        // Initialize inputs
        reset = 1;
        up_down = 1;
        #10 reset = 0;
        #50 up_down = 1;
        #50 up_down = 0;
        #30 reset = 1;
        #10 reset = 0;
        #100 $finish;
    end

    initial begin
        $monitor("At time %t, count = %d, up_down = %b", $time, count, up_down);
    end

    initial begin
        $dumpfile("waveform.vcd");
        $dumpvars(0, testbench);
    end

endmodule

rippleCounter.sim/sim_1/behav/xsim/waveform.vcd
$date
   Fri Jul 26 15:47:10 2024
$end
$version
  2022.2
$end
$timescale
  1ps
$end
$scope module testbench $end
$var reg 1 ! clk $end
$var reg 1 " reset $end
$var reg 1 # up_down $end
$var wire 3 $ count [2:0] $end
$scope module udc $end
$var wire 1 % clk $end
$var wire 1 & reset $end
$var wire 1 ' up_down $end
$var wire 3 $ count [2:0] $end
$var reg 3 ( count_reg [2:0] $end
$upscope $end
$upscope $end
$enddefinitions $end
#0
$dumpvars
0!
1"
1#
b0 $
0%
1&
1'
b0 (
$end
#5000
1!
1%
#10000
0!
0"
0%
0&
#15000
1!
b1 $
1%
b1 (
#20000
0!
0%
#25000
1!
b10 $
1%
b10 (
#30000
0!
0%
#35000
1!
b11 $
1%
b11 (
#40000
0!
0%
#45000
1!
b100 $
1%
b100 (
#50000
0!
0%
#55000
1!
b101 $
1%
b101 (
#60000
0!
0%
#65000
1!
b110 $
1%
b110 (
#70000
0!
0%
#75000
1!
b111 $
1%
b111 (
#80000
0!
0%
#85000
1!
b0 $
1%
b0 (
#90000
0!
0%
#95000
1!
b1 $
1%
b1 (
#100000
0!
0%
#105000
1!
b10 $
1%
b10 (
#110000
0!
0#
0%
0'
#115000
1!
b1 $
1%
b1 (
#120000
0!
0%
#125000
1!
b0 $
1%
b0 (
#130000
0!
0%
#135000
1!
b111 $
1%
b111 (
#140000
0!
1"
b0 $
0%
1&
b0 (
#145000
1!
1%
#150000
0!
0"
0%
0&
#155000
1!
b111 $
1%
b111 (
#160000
0!
0%
#165000
1!
b110 $
1%
b110 (
#170000
0!
0%
#175000
1!
b101 $
1%
b101 (
#180000
0!
0%
#185000
1!
b100 $
1%
b100 (
#190000
0!
0%
#195000
1!
b11 $
1%
b11 (
#200000
0!
0%
#205000
1!
b10 $
1%
b10 (
#210000
0!
0%
#215000
1!
b1 $
1%
b1 (
#220000
0!
0%
#225000
1!
b0 $
1%
b0 (
#230000
0!
0%
#235000
1!
b111 $
1%
b111 (
#240000
0!
0%
#245000
1!
b110 $
1%
b110 (
