binaryCounter4-bit.srcs/sources_1/new/binaryCounter4Bit.v
`timescale 1ns / 1ps

module binaryCounter4Bit(
    input RESET, CLK, 
    output reg [3:0] COUNT
    );
    
    always @ (posedge CLK) begin
        if(RESET == 0)
                COUNT <= 0;
        else begin
                if(COUNT == 4'b1010)
                        COUNT <= 0;
                else
                        COUNT <= COUNT + 1;               
        end
     end   
endmodule

binaryCounter4-bit.srcs/sim_1/new/binaryCounter4Bit_tb.v
`timescale 1ns / 1ps

module binaryCounter4Bit_tb;
        reg reset,clk;
        wire [3:0] count;
        
        binaryCounter4Bit uut (
                .RESET(reset),
                .CLK(clk),
                .COUNT(count)
         );
         
         always #5 clk = ~clk;
         
         initial begin
                $dumpfile("binaryCounter4Bit.vcd");
                $dumpvars;
                clk=0;
                #10 reset=1;
                #100 reset=0;
                #10 $finish;
        end        
                     
endmodule

binaryCounter4-bit.sim/sim_1/behav/xsim/binaryCounter4Bit.vcd
$date
   Thu Nov 28 14:27:13 2024
$end
$version
  2022.2
$end
$timescale
  1ps
$end
$scope module binaryCounter4Bit_tb $end
$var reg 1 ! reset $end
$var reg 1 " clk $end
$var wire 4 # count [3:0] $end
$scope module uut $end
$var wire 1 $ RESET $end
$var wire 1 % CLK $end
$var reg 4 & COUNT [3:0] $end
$upscope $end
$upscope $end
$enddefinitions $end
#0
$dumpvars
x!
0"
bx #
x$
0%
bx &
$end
#5000
1"
1%
bx &
#10000
1!
0"
1$
0%
#15000
1"
1%
bx &
#20000
0"
0%
#25000
1"
1%
bx &
#30000
0"
0%
#35000
1"
1%
bx &
#40000
0"
0%
#45000
1"
1%
bx &
#50000
0"
0%
#55000
1"
1%
bx &
#60000
0"
0%
#65000
1"
1%
bx &
#70000
0"
0%
#75000
1"
1%
bx &
#80000
0"
0%
#85000
1"
1%
bx &
#90000
0"
0%
#95000
1"
1%
bx &
#100000
0"
0%
#105000
1"
1%
bx &
#110000
0!
0"
0$
0%
#115000
1"
b0 #
1%
b0 &
