D_latch.srcs/sources_1/new/DFF.v
`timescale 1ns / 1ps

// DFF with SET and RESET
module DFF(
    input RESET, SET, EN, CLK, D,
    output reg Q
  );
  
  initial Q = 1'b0;

  
  always @(posedge  CLK) begin              //  Considering every positive edge
        if(EN == 1) begin                               // If DFF is enabled, begin used for more than one statements
            if (RESET == 0)                              //  If RESET is pressed
                Q <= 1'b0;                                  // RESET Q as 0   --- RESET has higher priority
            else begin
                if(SET == 0)                                //  If SET is pressed
                    Q <= 1'b1;                               // SET Q as 0
                else
                    Q <= D;     
            end   
        end          
        else
            Q <= Q;
  end                       
endmodule

D_latch.srcs/sim_1/new/DFF_tb.v
`timescale 1ns / 1ps
/*
module DFF_tb;
    reg reset, set, en, clk, d;
    wire q;
    
    DFF uut (
            .RESET(reset),
            .SET(set),
            .EN(en),
            .CLK(clk),
            .D(d),
            .Q(q)
    );
    
    
    // This block generates a clock signal (clk) that toggles every 5 time units (ns), creating a clock period of 10 ns (5 ns for high, 5 ns for low).
    always #5 clk = ~clk;   
    
    initial  begin 
        $dumpfile ("DFF.vcd");          // Creates a output file to record simulation data
        $dumpvars;                              // Record all data in above file
        
        clk = 0; d = 0; reset= 0; set = 0; en = 0;
        #20 en = 1;                  // enable the ENABLE
        #10 reset = 0;           // set the RESET as HIGH
        #20 reset = 1;          // set the RESET to LOW
        #10 set = 1;           // set the SET as HIGH
        #20 set = 0;            // set the SET as LOW
        #10 d =1;                
        #10 d =0;
        #30 en = 0;
        #30 $finish;
   end      
endmodule
*/


module DFF_tb;
    reg reset, set, en, clk, d;
    wire q;

    // Instantiate the DFF module
    DFF uut (
        .RESET(reset),
        .SET(set),
        .EN(en),
        .CLK(clk),
        .D(d),
        .Q(q)
    );

    // Generate a clock signal with a period of 10ns
    always #5 clk = ~clk;

    initial begin
        $dumpfile ("DFF.vcd");          // Creates a waveform dump file
        $dumpvars;                      // Records all variables in the file

        // Initialize all inputs
        clk = 0; d = 0; reset = 1; set = 1; en = 0;

        // Test sequence
        #20 en = 1;                     // Enable the flip-flop
        #10 reset = 1;                  // Keep reset inactive (HIGH)
        #20 set = 1;                    // Deactivate SET (HIGH)
        #10 d = 0;                      // Set D to 0
        #10 set = 0;                    // Activate SET briefly to force Q = 1
        #10 set = 1;                    // Deactivate SET again
        #10 d = 1;                      // Set D to 1
        #10 d = 0;                      // Set D to 0 (observe behavior)
        #30 en = 0;                     // Disable the flip-flop
        #30 $finish;                    // End the simulation
    end
endmodule

D_latch.sim/sim_1/behav/xsim/DFF.vcd
$date
   Thu Nov 28 10:35:33 2024
$end
$version
  2022.2
$end
$timescale
  1ps
$end
$scope module DFF_tb $end
$var reg 1 ! reset $end
$var reg 1 " set $end
$var reg 1 # en $end
$var reg 1 $ clk $end
$var reg 1 % d $end
$var wire 1 & q $end
$scope module uut $end
$var wire 1 ' RESET $end
$var wire 1 ( SET $end
$var wire 1 ) EN $end
$var wire 1 * CLK $end
$var wire 1 + D $end
$var reg 1 , Q $end
$upscope $end
$upscope $end
$enddefinitions $end
#0
$dumpvars
1!
1"
0#
0$
0%
0&
1'
1(
0)
0*
0+
0,
$end
#5000
1$
1*
0,
#10000
0$
0*
#15000
1$
1*
0,
#20000
1#
0$
1)
0*
#25000
1$
1*
0,
#30000
0$
0*
#35000
1$
1*
0,
#40000
0$
0*
#45000
1$
1*
0,
#50000
0$
0*
#55000
1$
1*
0,
#60000
0$
0*
#65000
1$
1*
0,
#70000
0"
0$
0(
0*
#75000
1$
1&
1*
1,
#80000
1"
0$
1(
0*
#85000
1$
0&
1*
0,
#90000
0$
1%
0*
1+
#95000
1$
1&
1*
1,
#100000
0$
0%
0*
0+
#105000
1$
0&
1*
0,
#110000
0$
0*
#115000
1$
1*
0,
#120000
0$
0*
#125000
1$
1*
0,
#130000
0#
0$
0)
0*
#135000
1$
1*
0,
#140000
0$
0*
#145000
1$
1*
0,
#150000
0$
0*
#155000
1$
1*
0,
